gusnet_epanet/__init__.py
gusnet_epanet/glnx/epanetmsx
gusnet_epanet/glnx/epanetmsx.so
gusnet_epanet/glnx/libepanet2
gusnet_epanet/glnx/libepanet2.so
gusnet_epanet/mac/epanetmsx
gusnet_epanet/mac/epanetmsx.dylib
gusnet_epanet/mac/libepanet2
gusnet_epanet/mac/libepanet2.dylib
gusnet_epanet/win/epanet2.dll
gusnet_epanet/win/epanet2.exe
gusnet_epanet/win/epanetmsx.dll
gusnet_epanet/win/epanetmsx.exe
gusnet_epanet-2.2.0.dist-info/METADATA
gusnet_epanet-2.2.0.dist-info/WHEEL
gusnet_epanet-2.2.0.dist-info/licenses/LICENSE
gusnet_epanet-2.2.0.dist-info/RECORD
