Metadata-Version: 2.4
Name: gusnet-epanet
Version: 2.2.0
Summary: To accompany the Gusnet QGIS plugin
Project-URL: Homepage, https://gusnet.org
Project-URL: Issues, https://github.com/angusmcb/gusnet/issues
Author-email: Angus McBride <pypi@zog.mozmail.com>
License-Expression: MIT
License-File: LICENSE
Classifier: Operating System :: OS Independent
Classifier: Programming Language :: Python :: 3
Requires-Python: >=3.9
